[
      {
            "date": "2023-12-19T00:00:00+07:00",
            "period": "YTD",
            "symbol": "GPSC",
            "market": "SET",
            "industry": "RESOURC",
            "sector": "ENERG",
            "prior": 73.0,
            "open": 73.5,
            "high": 75.5,
            "low": 37.0,
            "average": null,
            "close": 48.25,
            "change": -24.75,
            "percentChange": -33.9041095890411,
            "totalVolume": 1943466683.0,
            "totalValue": 105173679496.0,
            "pe": 48.94,
            "pbv": 1.26,
            "bookValuePerShare": 38.21,
            "dividendYield": 1.0399999618530273,
            "marketCap": 136051941957.75,
            "listedShare": 2819729367.0,
            "par": 10.0,
            "financialDate": "2023-09-30T00:00:00+07:00",
            "turnoverRatio": 68.92387282782802,
            "beta": 1.59,
            "dividendPayoutRatio": 0.61,
            "averageValue": 445651184.30508476
      },
      {
            "date": "2022-12-30T00:00:00+07:00",
            "period": "2022",
            "symbol": "GPSC",
            "market": "SET",
            "industry": "RESOURC",
            "sector": "ENERG",
            "prior": 88.75,
            "open": 89.0,
            "high": 89.25,
            "low": 57.25,
            "average": null,
            "close": 73.0,
            "change": -15.75,
            "percentChange": -17.746478873239436,
            "totalVolume": 2361128322.0,
            "totalValue": 167453524033.75,
            "pe": 82.46,
            "pbv": 1.92,
            "bookValuePerShare": 38.05,
            "dividendYield": 2.049999952316284,
            "marketCap": 205840243791.0,
            "listedShare": 2819729367.0,
            "par": 10.0,
            "financialDate": "2022-09-30T00:00:00+07:00",
            "turnoverRatio": 83.73599075261892,
            "beta": 1.25,
            "dividendPayoutRatio": 1.36,
            "averageValue": 694827900.5549792
      },
      {
            "date": "2021-12-30T00:00:00+07:00",
            "period": "2021",
            "symbol": "GPSC",
            "market": "SET",
            "industry": "RESOURC",
            "sector": "ENERG",
            "prior": 73.75,
            "open": 72.5,
            "high": 89.75,
            "low": 67.25,
            "average": null,
            "close": 88.75,
            "change": 15.0,
            "percentChange": 20.338983050847457,
            "totalVolume": 4044546569.0,
            "totalValue": 317297927897.75,
            "pe": 32.89,
            "pbv": 2.37,
            "bookValuePerShare": 37.4,
            "dividendYield": 1.690000057220459,
            "marketCap": 250250981321.25,
            "listedShare": 2819729367.0,
            "par": 10.0,
            "financialDate": "2021-09-30T00:00:00+07:00",
            "turnoverRatio": 143.43740276405043,
            "beta": 1.28,
            "dividendPayoutRatio": 0.56,
            "averageValue": 1316588912.4387968
      }
]