[
      {
            "date": "2023-12-19T00:00:00+07:00",
            "period": "YTD",
            "symbol": "INTUCH",
            "market": "SET",
            "industry": "TECH",
            "sector": "ICT",
            "prior": 77.25,
            "open": 77.5,
            "high": 78.75,
            "low": 67.75,
            "average": null,
            "close": 71.25,
            "change": -6.0,
            "percentChange": -7.766990291262136,
            "totalVolume": 942503393.0,
            "totalValue": 68948856506.87,
            "pe": 19.5,
            "pbv": 6.44,
            "bookValuePerShare": 11.07,
            "dividendYield": 6.619999885559082,
            "marketCap": 228476497556.25,
            "listedShare": 3206687685.0,
            "par": 1.0,
            "financialDate": "2023-09-30T00:00:00+07:00",
            "turnoverRatio": 29.39180505194724,
            "beta": 0.65,
            "dividendPayoutRatio": 1.21,
            "averageValue": 292156171.63927966
      },
      {
            "date": "2022-12-30T00:00:00+07:00",
            "period": "2022",
            "symbol": "INTUCH",
            "market": "SET",
            "industry": "TECH",
            "sector": "ICT",
            "prior": 80.25,
            "open": 80.75,
            "high": 81.0,
            "low": 67.0,
            "average": null,
            "close": 77.25,
            "change": -3.0,
            "percentChange": -3.7383177570093458,
            "totalVolume": 1080703468.0,
            "totalValue": 79370486237.9,
            "pe": 24.13,
            "pbv": 6.58,
            "bookValuePerShare": 11.74,
            "dividendYield": 3.6600000858306885,
            "marketCap": 247716623666.25,
            "listedShare": 3206687685.0,
            "par": 1.0,
            "financialDate": "2022-09-30T00:00:00+07:00",
            "turnoverRatio": 33.701943070108264,
            "beta": 0.58,
            "dividendPayoutRatio": 1.05,
            "averageValue": 329338117.1697095
      },
      {
            "date": "2021-12-30T00:00:00+07:00",
            "period": "2021",
            "symbol": "INTUCH",
            "market": "SET",
            "industry": "TECH",
            "sector": "ICT",
            "prior": 56.25,
            "open": 55.5,
            "high": 90.75,
            "low": 54.5,
            "average": null,
            "close": 80.25,
            "change": 24.0,
            "percentChange": 42.666666666666664,
            "totalVolume": 2881446116.0,
            "totalValue": 197818350371.18,
            "pe": 23.82,
            "pbv": 6.77,
            "bookValuePerShare": 11.86,
            "dividendYield": 3.119999885559082,
            "marketCap": 257329533396.75,
            "listedShare": 3206598547.0,
            "par": 1.0,
            "financialDate": "2021-09-30T00:00:00+07:00",
            "turnoverRatio": 89.86093221019387,
            "beta": 0.63,
            "dividendPayoutRatio": 0.77,
            "averageValue": 820823030.5858091
      }
]